eventables/__init__.py
eventables/events.py
eventables-0.1.0.dist-info/LICENSE
eventables-0.1.0.dist-info/METADATA
eventables-0.1.0.dist-info/WHEEL
eventables-0.1.0.dist-info/top_level.txt
eventables-0.1.0.dist-info/RECORD
