Metadata-Version: 2.1
Name: eventables
Version: 0.1.0
Summary: Simple Event handler with custom objects for tracking realtime data changes
Author-email: Alex Carroll <CarrollAutomation@gmail.com>
Project-URL: Homepage, https://github.com/CarrollAutomation/Eventables
Project-URL: Bug Tracker, https://github.com/CarrollAutomation/Eventables/issues
Classifier: Programming Language :: Python :: 3
Classifier: License :: OSI Approved :: MIT License
Classifier: Operating System :: OS Independent
License-File: LICENSE
